conf.py
pyweb.py
tangle.py
weave.py
py_web_lp-3.2.1.dist-info/LICENSE
py_web_lp-3.2.1.dist-info/METADATA
py_web_lp-3.2.1.dist-info/WHEEL
py_web_lp-3.2.1.dist-info/top_level.txt
py_web_lp-3.2.1.dist-info/RECORD
