Metadata-Version: 2.1
Name: py-web-lp
Version: 3.2.1
Summary: py-web-lp: Yet Another Literate Programming Tool
Author-email: "S.Lott" <slott56@gmail.com>
License: BSD
Project-URL: repository, https://github.com/slott56/py-web-tool
Project-URL: documentation, https://slott56.github.io/py-web-tool/src/pyweb.html
Classifier: Development Status :: 5 - Production/Stable
Classifier: Environment :: Console
Classifier: Intended Audience :: Developers
Classifier: License :: OSI Approved :: BSD License
Classifier: Operating System :: OS Independent
Classifier: Programming Language :: Python :: 3 :: Only
Classifier: Programming Language :: Python :: 3.10
Classifier: Programming Language :: Python :: 3.11
Classifier: Programming Language :: Python
Classifier: Topic :: Documentation
Classifier: Topic :: Software Development :: Documentation
Classifier: Topic :: System :: Systems Administration
Classifier: Topic :: Text Processing :: Markup
Classifier: Typing :: Typed
Requires-Python: >=3.10
License-File: LICENSE
Requires-Dist: jinja2 (==3.1.2)
Requires-Dist: setuptools
Requires-Dist: wheel
Requires-Dist: tomli ; python_version < "3.11"
Provides-Extra: dev
Requires-Dist: sphinx (==7.0.1) ; extra == 'dev'
Requires-Dist: sphinxcontrib-plantuml (==1.0.0) ; extra == 'dev'
Requires-Dist: docutils (==0.20.1) ; extra == 'dev'
Requires-Dist: build ; extra == 'dev'
Requires-Dist: twine ; extra == 'dev'
Provides-Extra: test
Requires-Dist: tox (==4.6.4) ; extra == 'test'
Requires-Dist: pytest (==7.4.0) ; extra == 'test'
Requires-Dist: mypy (==1.4.1) ; extra == 'test'
